funniestDemo/__init__.py
funniestDemo/__main__.py
funniestDemo/buddha.txt
funniestDemo/command_line.py
funniestDemo-0.72.dist-info/METADATA
funniestDemo-0.72.dist-info/WHEEL
funniestDemo-0.72.dist-info/entry_points.txt
funniestDemo-0.72.dist-info/top_level.txt
funniestDemo-0.72.dist-info/RECORD
