Metadata-Version: 2.1
Name: funniestDemo
Version: 0.72
Summary: Demo to make a python package
Home-page: https://github.com/Junch/funniestDemo
Author: Jun Chen
Author-email: junc76@gmail.com
License: UNKNOWN
Platform: UNKNOWN
Classifier: Programming Language :: Python :: 3
Classifier: License :: OSI Approved :: MIT License
Classifier: Operating System :: OS Independent
Requires-Python: >=3.7
